alcedo-0.1.7.dist-info/METADATA
alcedo-0.1.7.dist-info/WHEEL
alcedo-0.1.7.dist-info/license_files/LICENSE
alcedo/__init__.py
alcedo/__init__.pyi
alcedo/py.typed
alcedo/alcedo.cpython-312-darwin.so
alcedo-0.1.7.dist-info/RECORD
